cm_text/__init__.py
cm_text/channels.py
cm_text/gateways.py
cm_text/message.py
cm_text/message_body_types.py
cm_text/text_client.py
cm_text/text_client_status_codes.py
cm_text/version.py
cm_text/whatsapp_template.py
cm_text/whatsapp_interactive/__init__.py
cm_text/whatsapp_interactive/interactive_message.py
cm_text/whatsapp_interactive/message_action.py
cm_text/whatsapp_interactive/message_body.py
cm_text/whatsapp_interactive/message_builder.py
cm_text/whatsapp_interactive/message_footer.py
cm_text/whatsapp_interactive/message_header.py
cm_text_sdk_python-2.0.4.dist-info/LICENSE
cm_text_sdk_python-2.0.4.dist-info/METADATA
cm_text_sdk_python-2.0.4.dist-info/WHEEL
cm_text_sdk_python-2.0.4.dist-info/top_level.txt
cm_text_sdk_python-2.0.4.dist-info/RECORD
