Metadata-Version: 2.1
Name: cm_text_sdk_python
Version: 2.0.4
Summary: Python SDK for text with CM.
Home-page: https://github.com/cmdotcom/text-sdk-python
Author: Joris Pennings
Author-email: joris.pennings@cm.com
Classifier: Programming Language :: Python :: 3
Classifier: License :: OSI Approved :: MIT License
Classifier: Operating System :: OS Independent
Requires-Python: >=3.6
License-File: LICENSE
